[
  {
    "anonymous": false,
    "inputs": [
      {
        "indexed": true,
        "internalType": "address",
        "name": "idProxyAddress",
        "type": "address"
      },
      {
        "indexed": true,
        "internalType": "uint256",
        "name": "nodeId",
        "type": "uint256"
      },
      {
        "indexed": true,
        "internalType": "address",
        "name": "beneficiary",
        "type": "address"
      }
    ],
    "name": "BeneficiarySet",
    "type": "event"
  },
  {
    "inputs": [
      {
        "internalType": "address",
        "name": "idProxyAddress",
        "type": "address"
      },
      {
        "internalType": "uint256",
        "name": "nodeId",
        "type": "uint256"
      }
    ],
    "name": "getBeneficiary",
    "outputs": [
      {
        "internalType": "address",
        "name": "beneficiary",
        "type": "address"
      }
    ],
    "stateMutability": "view",
    "type": "function"
  },
  {
    "inputs": [
      {
        "internalType": "address",
        "name": "idProxyAddress",
        "type": "address"
      },
      {
        "internalType": "uint256",
        "name": "sourceNode",
        "type": "uint256"
      }
    ],
    "name": "getLink",
    "outputs": [
      {
        "internalType": "uint256",
        "name": "targetNode",
        "type": "uint256"
      }
    ],
    "stateMutability": "view",
    "type": "function"
  },
  {
    "inputs": [
      {
        "internalType": "address",
        "name": "idProxyAddressSource",
        "type": "address"
      },
      {
        "internalType": "address",
        "name": "idProxyAddressTarget",
        "type": "address"
      },
      {
        "internalType": "uint256",
        "name": "sourceNode",
        "type": "uint256"
      }
    ],
    "name": "getNodeLink",
    "outputs": [
      {
        "internalType": "uint256",
        "name": "targetNode",
        "type": "uint256"
      }
    ],
    "stateMutability": "view",
    "type": "function"
  },
  {
    "inputs": [
      {
        "internalType": "uint256",
        "name": "nodeId",
        "type": "uint256"
      },
      {
        "internalType": "address",
        "name": "beneficiary",
        "type": "address"
      }
    ],
    "name": "setAftermarketDeviceBeneficiary",
    "outputs": [],
    "stateMutability": "nonpayable",
    "type": "function"
  }
]
